{
  "chapter": {
    "id": "8ff4a0e1-8e24-4f99-8fea-f6df0c9be018",
    "number": 87,
    "ref": "https://www.biblegateway.com/passage/?search=Th%C3%A1nh%20Thi%2087&version=BD2011",
    "createdAt": "2025-04-22T07:37:47.657Z",
    "updatedAt": "2025-04-22T07:37:47.657Z",
    "bookId": "7a44f33e-f512-4e76-bac1-934bef7677e1"
  },
  "verses": [
    {
      "id": "f1e7df80-8a36-4aa8-8bc7-9238cfb922f7",
      "number": 1,
      "content": "Chúa lập nền cho thành của Ngài trên núi thánh.",
      "order": 0,
      "parNumber": 0,
      "parIndex": 0,
      "isPoetry": true,
      "createdAt": "2025-04-22T08:30:01.020Z",
      "updatedAt": "2025-04-22T08:30:01.020Z",
      "chapterId": "8ff4a0e1-8e24-4f99-8fea-f6df0c9be018"
    },
    {
      "id": "9cf786f7-4d65-40a4-a965-ab7c14120c41",
      "number": 2,
      "content": "Chúa yêu mến các cổng thành của Si-ôn hơn mọi nơi cư trú của Gia-cốp.",
      "order": 0,
      "parNumber": 0,
      "parIndex": 1,
      "isPoetry": true,
      "createdAt": "2025-04-22T08:30:01.048Z",
      "updatedAt": "2025-04-22T08:30:01.048Z",
      "chapterId": "8ff4a0e1-8e24-4f99-8fea-f6df0c9be018"
    },
    {
      "id": "78a534a4-c70b-4e08-85aa-b5612c5aee08",
      "number": 3,
      "content": "Hỡi thành của Ðức Chúa Trời,",
      "order": 0,
      "parNumber": 0,
      "parIndex": 2,
      "isPoetry": true,
      "createdAt": "2025-04-22T08:30:01.059Z",
      "updatedAt": "2025-04-22T08:30:01.059Z",
      "chapterId": "8ff4a0e1-8e24-4f99-8fea-f6df0c9be018"
    },
    {
      "id": "dc3d8ebb-4331-4e33-b823-48d722cacb51",
      "number": 3,
      "content": "Thiên hạ đã nói nhiều điều vinh hiển về ngươi. *(Sê-la)*",
      "order": 1,
      "parNumber": 0,
      "parIndex": 3,
      "isPoetry": true,
      "createdAt": "2025-04-22T08:30:01.069Z",
      "updatedAt": "2025-04-22T08:30:01.069Z",
      "chapterId": "8ff4a0e1-8e24-4f99-8fea-f6df0c9be018"
    },
    {
      "id": "c495a6b4-609e-4aa0-900c-07b76f1bab3b",
      "number": 4,
      "content": "Khi tôi nhắc đến Ai-cập và Ba-by-lôn cho những ai biết tôi,",
      "order": 0,
      "parNumber": 1,
      "parIndex": 0,
      "isPoetry": true,
      "createdAt": "2025-04-22T08:30:01.079Z",
      "updatedAt": "2025-04-22T08:30:01.079Z",
      "chapterId": "8ff4a0e1-8e24-4f99-8fea-f6df0c9be018"
    },
    {
      "id": "22c235ef-8aaa-4416-9f82-1add4000c10f",
      "number": 4,
      "content": "Hoặc đề cập đến Phi-li-tin, Ty-rơ, với Ê-thi-ô-pi,",
      "order": 1,
      "parNumber": 1,
      "parIndex": 1,
      "isPoetry": true,
      "createdAt": "2025-04-22T08:30:01.100Z",
      "updatedAt": "2025-04-22T08:30:01.100Z",
      "chapterId": "8ff4a0e1-8e24-4f99-8fea-f6df0c9be018"
    },
    {
      "id": "8d3f5344-5e37-4bd6-bb81-b93c055d3655",
      "number": 4,
      "content": "Thì người ta bảo, “Người này đã sinh trưởng tại Si-ôn đó!”",
      "order": 2,
      "parNumber": 1,
      "parIndex": 2,
      "isPoetry": true,
      "createdAt": "2025-04-22T08:30:01.111Z",
      "updatedAt": "2025-04-22T08:30:01.111Z",
      "chapterId": "8ff4a0e1-8e24-4f99-8fea-f6df0c9be018"
    },
    {
      "id": "5b200824-849e-4397-bdbf-612f1fbd0591",
      "number": 5,
      "content": "Thật vậy Si-ôn sẽ được trầm trồ khen ngợi rằng,",
      "order": 0,
      "parNumber": 2,
      "parIndex": 0,
      "isPoetry": true,
      "createdAt": "2025-04-22T08:30:01.135Z",
      "updatedAt": "2025-04-22T08:30:01.135Z",
      "chapterId": "8ff4a0e1-8e24-4f99-8fea-f6df0c9be018"
    },
    {
      "id": "d0919181-7cd3-49ab-a95e-ff421bbd347a",
      "number": 5,
      "content": "“Người này và người nọ đã sinh trưởng trong thành ấy!”",
      "order": 1,
      "parNumber": 2,
      "parIndex": 1,
      "isPoetry": true,
      "createdAt": "2025-04-22T08:30:01.145Z",
      "updatedAt": "2025-04-22T08:30:01.145Z",
      "chapterId": "8ff4a0e1-8e24-4f99-8fea-f6df0c9be018"
    },
    {
      "id": "649888e5-0b89-4e45-825b-62cb13ca675e",
      "number": 5,
      "content": "Chính Ðấng Tối Cao sẽ làm cho thành ấy được vững bền.",
      "order": 2,
      "parNumber": 2,
      "parIndex": 2,
      "isPoetry": true,
      "createdAt": "2025-04-22T08:30:01.155Z",
      "updatedAt": "2025-04-22T08:30:01.155Z",
      "chapterId": "8ff4a0e1-8e24-4f99-8fea-f6df0c9be018"
    },
    {
      "id": "8204b629-67be-4084-9f0e-a56ad9b4e5da",
      "number": 6,
      "content": "Chúa sẽ ghi vào sổ hộ tịch của các dân rằng,",
      "order": 0,
      "parNumber": 2,
      "parIndex": 3,
      "isPoetry": true,
      "createdAt": "2025-04-22T08:30:01.165Z",
      "updatedAt": "2025-04-22T08:30:01.165Z",
      "chapterId": "8ff4a0e1-8e24-4f99-8fea-f6df0c9be018"
    },
    {
      "id": "3b3445c2-7f0b-4caa-9097-e53611e0b26d",
      "number": 6,
      "content": "“Người này đã sinh ra tại Si-ôn.” *(Sê-la)*",
      "order": 1,
      "parNumber": 2,
      "parIndex": 4,
      "isPoetry": true,
      "createdAt": "2025-04-22T08:30:01.175Z",
      "updatedAt": "2025-04-22T08:30:01.175Z",
      "chapterId": "8ff4a0e1-8e24-4f99-8fea-f6df0c9be018"
    },
    {
      "id": "583b675d-e427-481d-8aa8-c61f3dd2a61d",
      "number": 7,
      "content": "Rồi những ca sĩ và nhạc sĩ sẽ nói,",
      "order": 0,
      "parNumber": 2,
      "parIndex": 5,
      "isPoetry": true,
      "createdAt": "2025-04-22T08:30:01.195Z",
      "updatedAt": "2025-04-22T08:30:01.195Z",
      "chapterId": "8ff4a0e1-8e24-4f99-8fea-f6df0c9be018"
    },
    {
      "id": "bdfe881e-c6fb-42cc-aae3-cdf55aec2edf",
      "number": 7,
      "content": "“Tất cả nguồn cảm hứng của tôi đều phát xuất từ Si-ôn.”",
      "order": 1,
      "parNumber": 2,
      "parIndex": 6,
      "isPoetry": true,
      "createdAt": "2025-04-22T08:30:01.206Z",
      "updatedAt": "2025-04-22T08:30:01.206Z",
      "chapterId": "8ff4a0e1-8e24-4f99-8fea-f6df0c9be018"
    }
  ],
  "footnotes": [
    {
      "id": "9499bb6d-4d48-48a1-8f4d-94f26831e5cb",
      "content": "nt: Ra-háp (Ra-háp là tên của một thủy quái thời xưa tiêu biểu cho Ai-cập)",
      "position": 23,
      "order": 0,
      "createdAt": "2025-04-22T08:30:01.090Z",
      "updatedAt": "2025-04-22T08:30:01.090Z",
      "verseId": "c495a6b4-609e-4aa0-900c-07b76f1bab3b",
      "chapterId": "8ff4a0e1-8e24-4f99-8fea-f6df0c9be018"
    },
    {
      "id": "b30f1992-6d94-42c9-bbe7-f3a1031dd113",
      "content": "nt: tại đó",
      "position": 58,
      "order": 1,
      "createdAt": "2025-04-22T08:30:01.121Z",
      "updatedAt": "2025-04-22T08:30:01.121Z",
      "verseId": "8d3f5344-5e37-4bd6-bb81-b93c055d3655",
      "chapterId": "8ff4a0e1-8e24-4f99-8fea-f6df0c9be018"
    },
    {
      "id": "8f1587e7-243d-4caa-974d-e4a16e1ca9f7",
      "content": "nt: tại đó",
      "position": 33,
      "order": 2,
      "createdAt": "2025-04-22T08:30:01.185Z",
      "updatedAt": "2025-04-22T08:30:01.185Z",
      "verseId": "3b3445c2-7f0b-4caa-9097-e53611e0b26d",
      "chapterId": "8ff4a0e1-8e24-4f99-8fea-f6df0c9be018"
    }
  ],
  "headings": [
    {
      "id": "da0f202a-8d2d-4a2f-9cb6-ce8a5582352d",
      "content": "Vinh Hạnh của Cư Dân Si-ôn",
      "level": 1,
      "order": 0,
      "createdAt": "2025-04-22T08:30:01.037Z",
      "updatedAt": "2025-04-22T08:30:01.037Z",
      "verseId": "f1e7df80-8a36-4aa8-8bc7-9238cfb922f7",
      "chapterId": "8ff4a0e1-8e24-4f99-8fea-f6df0c9be018"
    }
  ],
  "references": [],
  "psalmMetadata": [
    {
      "id": "a7236296-3bed-41ee-9190-1efbc71afa65",
      "title": "Một thi ca của con cháu Cô-ra",
      "createdAt": "2025-04-22T08:30:03.360Z",
      "updatedAt": "2025-04-22T08:30:03.360Z",
      "chapterId": "8ff4a0e1-8e24-4f99-8fea-f6df0c9be018"
    }
  ]
}