{
  "chapter": {
    "id": "bc971b4a-1697-40d9-a291-63723b8d05ef",
    "number": 16,
    "ref": "https://www.bible.com/bible/19/1CH.16.BD2011",
    "createdAt": "2025-04-24T01:29:04.033Z",
    "updatedAt": "2025-04-24T01:29:04.033Z",
    "bookId": "feeb7269-4345-48a2-84ee-f8d779e9abfc"
  },
  "verses": [
    {
      "id": "49a13cff-63bd-43be-a95a-2bba74eceb39",
      "number": 1,
      "content": "Vậy họ rước Rương của Đức Chúa Trời và đặt Rương Thánh vào lều Đa-vít đã dựng cho Rương Thánh. Sau đó họ dâng các của lễ thiêu và các lễ cầu an trước thánh nhan của Đức Chúa Trời.",
      "order": 0,
      "parNumber": 0,
      "parIndex": 0,
      "isPoetry": false,
      "createdAt": "2025-04-24T01:45:08.921Z",
      "updatedAt": "2025-04-24T01:45:08.921Z",
      "chapterId": "bc971b4a-1697-40d9-a291-63723b8d05ef"
    },
    {
      "id": "54c577a5-7006-41a7-b6ed-7bd913c22361",
      "number": 2,
      "content": "Sau khi Đa-vít đã dâng các của lễ thiêu và các của lễ cầu an, ông nhân danh **CHÚA** chúc phước cho dân.",
      "order": 0,
      "parNumber": 0,
      "parIndex": 1,
      "isPoetry": false,
      "createdAt": "2025-04-24T01:45:08.948Z",
      "updatedAt": "2025-04-24T01:45:08.948Z",
      "chapterId": "bc971b4a-1697-40d9-a291-63723b8d05ef"
    },
    {
      "id": "77c31bd9-bc2d-40b6-8ce0-2c70d5a52e8e",
      "number": 3,
      "content": "Kế đó ông phát cho mọi người I-sơ-ra-ên, không phân biệt nam hay nữ, mỗi người một ổ bánh, một phần thịt, và một cái bánh nho khô.",
      "order": 0,
      "parNumber": 0,
      "parIndex": 2,
      "isPoetry": false,
      "createdAt": "2025-04-24T01:45:08.958Z",
      "updatedAt": "2025-04-24T01:45:08.958Z",
      "chapterId": "bc971b4a-1697-40d9-a291-63723b8d05ef"
    },
    {
      "id": "2f44f512-cf5d-4ab5-9bfe-512d0bfd0a7d",
      "number": 4,
      "content": "Ông bổ nhiệm một số người Lê-vi vào chức vụ hầu việc trước Rương của **CHÚA** để cầu xin, cảm tạ, và ca ngợi **CHÚA**, Đức Chúa Trời của I-sơ-ra-ên.",
      "order": 0,
      "parNumber": 1,
      "parIndex": 0,
      "isPoetry": false,
      "createdAt": "2025-04-24T01:45:08.972Z",
      "updatedAt": "2025-04-24T01:45:08.972Z",
      "chapterId": "bc971b4a-1697-40d9-a291-63723b8d05ef"
    },
    {
      "id": "2dfc8840-afc2-49c6-9ee3-cc778fc039ac",
      "number": 5,
      "content": "A-sáp làm trưởng; Xa-cha-ri-a làm phó; kế đến là Giê-i-ên, Sê-mi-ra-mốt, Giê-hi-ên, Mát-ti-thi-a, Ê-li-áp, Bê-na-gia, Ô-bết Ê-đôm, và Giê-i-ên để họ sử dụng các hạc cầm và các đàn lia; A-sáp là người sử dụng khánh chiêng.",
      "order": 0,
      "parNumber": 1,
      "parIndex": 1,
      "isPoetry": false,
      "createdAt": "2025-04-24T01:45:08.983Z",
      "updatedAt": "2025-04-24T01:45:08.983Z",
      "chapterId": "bc971b4a-1697-40d9-a291-63723b8d05ef"
    },
    {
      "id": "41a12a99-d29e-4d71-8fae-b0b15d8a3afe",
      "number": 6,
      "content": "Còn hai vị tư tế Bê-na-gia và Gia-ha-xi-ên có nhiệm vụ thổi kèn thường xuyên trước Rương Giao Ước của Đức Chúa Trời.",
      "order": 0,
      "parNumber": 1,
      "parIndex": 2,
      "isPoetry": false,
      "createdAt": "2025-04-24T01:45:08.995Z",
      "updatedAt": "2025-04-24T01:45:08.995Z",
      "chapterId": "bc971b4a-1697-40d9-a291-63723b8d05ef"
    },
    {
      "id": "e2551a0f-d9e7-4ac9-958e-3138f3300bb6",
      "number": 7,
      "content": "Ngày hôm đó lần đầu tiên Đa-vít đưa cho A-sáp và bà con của ông ấy những bài thánh thi để hát lên cảm tạ **CHÚA**:",
      "order": 0,
      "parNumber": 2,
      "parIndex": 0,
      "isPoetry": false,
      "createdAt": "2025-04-24T01:45:09.006Z",
      "updatedAt": "2025-04-24T01:45:09.006Z",
      "chapterId": "bc971b4a-1697-40d9-a291-63723b8d05ef"
    },
    {
      "id": "c2273a23-ae6b-4be9-8c3d-be967e641a25",
      "number": 8,
      "content": "Hãy cảm tạ **CHÚA**, hãy cầu khẩn danh Ngài;",
      "order": 0,
      "parNumber": 3,
      "parIndex": 0,
      "isPoetry": true,
      "createdAt": "2025-04-24T01:45:09.044Z",
      "updatedAt": "2025-04-24T01:45:09.044Z",
      "chapterId": "bc971b4a-1697-40d9-a291-63723b8d05ef"
    },
    {
      "id": "750c92be-cba3-4a30-87b6-9f42d58bb305",
      "number": 8,
      "content": "Hãy rao truyền cho các dân biết các công việc Ngài.",
      "order": 1,
      "parNumber": 4,
      "parIndex": 0,
      "isPoetry": true,
      "createdAt": "2025-04-24T01:45:09.054Z",
      "updatedAt": "2025-04-24T01:45:09.054Z",
      "chapterId": "bc971b4a-1697-40d9-a291-63723b8d05ef"
    },
    {
      "id": "85dbadd5-ac54-4dae-a2ac-12671cf4d82a",
      "number": 9,
      "content": "Hãy ca ngợi Ngài, hãy ca hát chúc tụng Ngài;",
      "order": 0,
      "parNumber": 5,
      "parIndex": 0,
      "isPoetry": true,
      "createdAt": "2025-04-24T01:45:09.067Z",
      "updatedAt": "2025-04-24T01:45:09.067Z",
      "chapterId": "bc971b4a-1697-40d9-a291-63723b8d05ef"
    },
    {
      "id": "10ad2c38-fdea-46fb-802a-19ea138075a4",
      "number": 9,
      "content": "Hãy kể ra tất cả những việc lạ lùng của Ngài.",
      "order": 1,
      "parNumber": 6,
      "parIndex": 0,
      "isPoetry": true,
      "createdAt": "2025-04-24T01:45:09.081Z",
      "updatedAt": "2025-04-24T01:45:09.081Z",
      "chapterId": "bc971b4a-1697-40d9-a291-63723b8d05ef"
    },
    {
      "id": "b17ecc03-12b8-4991-aea0-062d08310d9d",
      "number": 10,
      "content": "Vinh hiển thay cho người được ở trong danh thánh Ngài;",
      "order": 0,
      "parNumber": 7,
      "parIndex": 0,
      "isPoetry": true,
      "createdAt": "2025-04-24T01:45:09.093Z",
      "updatedAt": "2025-04-24T01:45:09.093Z",
      "chapterId": "bc971b4a-1697-40d9-a291-63723b8d05ef"
    },
    {
      "id": "1c56f0db-322d-4c59-8215-8ec2a9a4ace1",
      "number": 10,
      "content": "Nguyện lòng những người tìm kiếm **CHÚA** được vui mừng.",
      "order": 1,
      "parNumber": 8,
      "parIndex": 0,
      "isPoetry": true,
      "createdAt": "2025-04-24T01:45:09.105Z",
      "updatedAt": "2025-04-24T01:45:09.105Z",
      "chapterId": "bc971b4a-1697-40d9-a291-63723b8d05ef"
    },
    {
      "id": "46df4687-7968-40ad-bedd-908702f866ce",
      "number": 11,
      "content": "Hãy tìm kiếm **CHÚA** và tìm kiếm quyền năng Ngài;",
      "order": 0,
      "parNumber": 9,
      "parIndex": 0,
      "isPoetry": true,
      "createdAt": "2025-04-24T01:45:09.119Z",
      "updatedAt": "2025-04-24T01:45:09.119Z",
      "chapterId": "bc971b4a-1697-40d9-a291-63723b8d05ef"
    },
    {
      "id": "6ba6a0cf-449f-4695-9e5e-00a62afbcdc9",
      "number": 11,
      "content": "Hãy tìm kiếm mặt Ngài luôn luôn.",
      "order": 1,
      "parNumber": 10,
      "parIndex": 0,
      "isPoetry": true,
      "createdAt": "2025-04-24T01:45:09.133Z",
      "updatedAt": "2025-04-24T01:45:09.133Z",
      "chapterId": "bc971b4a-1697-40d9-a291-63723b8d05ef"
    },
    {
      "id": "3fc06c45-b4a5-4aaa-a6af-ca53b7751164",
      "number": 12,
      "content": "Hãy nhớ mãi những việc lạ lùng Ngài làm,",
      "order": 0,
      "parNumber": 11,
      "parIndex": 0,
      "isPoetry": true,
      "createdAt": "2025-04-24T01:45:09.147Z",
      "updatedAt": "2025-04-24T01:45:09.147Z",
      "chapterId": "bc971b4a-1697-40d9-a291-63723b8d05ef"
    },
    {
      "id": "94d01832-e6d2-40ea-aeaa-00aa114828b9",
      "number": 12,
      "content": "Tức những việc diệu kỳ và những phán quyết Ngài đã phán.",
      "order": 1,
      "parNumber": 12,
      "parIndex": 0,
      "isPoetry": true,
      "createdAt": "2025-04-24T01:45:09.164Z",
      "updatedAt": "2025-04-24T01:45:09.164Z",
      "chapterId": "bc971b4a-1697-40d9-a291-63723b8d05ef"
    },
    {
      "id": "e5a366f1-83ec-49ad-9056-4852c614590a",
      "number": 13,
      "content": "Hỡi dòng dõi của I-sơ-ra-ên, tôi tớ Ngài,",
      "order": 0,
      "parNumber": 13,
      "parIndex": 0,
      "isPoetry": true,
      "createdAt": "2025-04-24T01:45:09.177Z",
      "updatedAt": "2025-04-24T01:45:09.177Z",
      "chapterId": "bc971b4a-1697-40d9-a291-63723b8d05ef"
    },
    {
      "id": "8ac1317a-f0a0-4d61-a418-dc3524b6d553",
      "number": 13,
      "content": "Hỡi con cháu của Gia-cốp, những người Ngài đã chọn.",
      "order": 1,
      "parNumber": 14,
      "parIndex": 0,
      "isPoetry": true,
      "createdAt": "2025-04-24T01:45:09.204Z",
      "updatedAt": "2025-04-24T01:45:09.204Z",
      "chapterId": "bc971b4a-1697-40d9-a291-63723b8d05ef"
    },
    {
      "id": "7422d8df-1203-4603-8c70-134204f5b184",
      "number": 14,
      "content": "Ngài là **CHÚA**, Đức Chúa Trời chúng ta;",
      "order": 0,
      "parNumber": 15,
      "parIndex": 0,
      "isPoetry": true,
      "createdAt": "2025-04-24T01:45:09.218Z",
      "updatedAt": "2025-04-24T01:45:09.218Z",
      "chapterId": "bc971b4a-1697-40d9-a291-63723b8d05ef"
    },
    {
      "id": "5eadff82-84f2-4de0-8357-f73ec55c4826",
      "number": 14,
      "content": "Các phán quyết của Ngài là định luật cho cả địa cầu.",
      "order": 1,
      "parNumber": 16,
      "parIndex": 0,
      "isPoetry": true,
      "createdAt": "2025-04-24T01:45:09.231Z",
      "updatedAt": "2025-04-24T01:45:09.231Z",
      "chapterId": "bc971b4a-1697-40d9-a291-63723b8d05ef"
    },
    {
      "id": "6291b5e4-0610-4633-b0ed-61a94c73e562",
      "number": 15,
      "content": "Ngài ghi nhớ giao ước của Ngài mãi mãi,",
      "order": 0,
      "parNumber": 17,
      "parIndex": 0,
      "isPoetry": true,
      "createdAt": "2025-04-24T01:45:09.245Z",
      "updatedAt": "2025-04-24T01:45:09.245Z",
      "chapterId": "bc971b4a-1697-40d9-a291-63723b8d05ef"
    },
    {
      "id": "988e39c2-3e7e-4da1-9140-c12c6435476a",
      "number": 15,
      "content": "Lời Ngài đã truyền có hiệu lực cho ngàn thế hệ về sau,",
      "order": 1,
      "parNumber": 18,
      "parIndex": 0,
      "isPoetry": true,
      "createdAt": "2025-04-24T01:45:09.258Z",
      "updatedAt": "2025-04-24T01:45:09.258Z",
      "chapterId": "bc971b4a-1697-40d9-a291-63723b8d05ef"
    },
    {
      "id": "347c9d3a-e12a-44bf-b4d2-c6ea5b979c52",
      "number": 16,
      "content": "Ấy là giao ước Ngài đã lập với Áp-ra-ham,",
      "order": 0,
      "parNumber": 19,
      "parIndex": 0,
      "isPoetry": true,
      "createdAt": "2025-04-24T01:45:09.272Z",
      "updatedAt": "2025-04-24T01:45:09.272Z",
      "chapterId": "bc971b4a-1697-40d9-a291-63723b8d05ef"
    },
    {
      "id": "948589ba-2297-4509-b286-53428fc9c320",
      "number": 16,
      "content": "Và lời thề Ngài đã thề cùng I-sác.",
      "order": 1,
      "parNumber": 20,
      "parIndex": 0,
      "isPoetry": true,
      "createdAt": "2025-04-24T01:45:09.285Z",
      "updatedAt": "2025-04-24T01:45:09.285Z",
      "chapterId": "bc971b4a-1697-40d9-a291-63723b8d05ef"
    },
    {
      "id": "fca0a12b-a019-487a-abc0-47442e90037e",
      "number": 17,
      "content": "Sau đó Ngài đã xác nhận với Gia-cốp như một đạo luật,",
      "order": 0,
      "parNumber": 21,
      "parIndex": 0,
      "isPoetry": true,
      "createdAt": "2025-04-24T01:45:09.299Z",
      "updatedAt": "2025-04-24T01:45:09.299Z",
      "chapterId": "bc971b4a-1697-40d9-a291-63723b8d05ef"
    },
    {
      "id": "229d655e-9187-4794-812c-d697da9eb915",
      "number": 17,
      "content": "Với I-sơ-ra-ên như một giao ước đời đời,",
      "order": 1,
      "parNumber": 22,
      "parIndex": 0,
      "isPoetry": true,
      "createdAt": "2025-04-24T01:45:09.313Z",
      "updatedAt": "2025-04-24T01:45:09.313Z",
      "chapterId": "bc971b4a-1697-40d9-a291-63723b8d05ef"
    },
    {
      "id": "85d801e7-9f26-4b5d-a50f-518f0e795df1",
      "number": 18,
      "content": "Rằng, “Ta sẽ ban xứ Ca-na-an",
      "order": 0,
      "parNumber": 23,
      "parIndex": 0,
      "isPoetry": true,
      "createdAt": "2025-04-24T01:45:09.326Z",
      "updatedAt": "2025-04-24T01:45:09.326Z",
      "chapterId": "bc971b4a-1697-40d9-a291-63723b8d05ef"
    },
    {
      "id": "d7966507-432b-4545-aa66-b99b1908551d",
      "number": 18,
      "content": "Cho các ngươi để làm sản nghiệp,”",
      "order": 1,
      "parNumber": 24,
      "parIndex": 0,
      "isPoetry": true,
      "createdAt": "2025-04-24T01:45:09.339Z",
      "updatedAt": "2025-04-24T01:45:09.339Z",
      "chapterId": "bc971b4a-1697-40d9-a291-63723b8d05ef"
    },
    {
      "id": "371ee8eb-7d44-492e-b309-9b5793b7296d",
      "number": 19,
      "content": "Trong khi họ chỉ là một số ít người,",
      "order": 0,
      "parNumber": 25,
      "parIndex": 0,
      "isPoetry": true,
      "createdAt": "2025-04-24T01:45:09.353Z",
      "updatedAt": "2025-04-24T01:45:09.353Z",
      "chapterId": "bc971b4a-1697-40d9-a291-63723b8d05ef"
    },
    {
      "id": "b6a59072-2c1a-4532-b40d-87cf45c97ef4",
      "number": 19,
      "content": "Một nhóm thiểu số và là những kiều dân trong xứ.",
      "order": 1,
      "parNumber": 26,
      "parIndex": 0,
      "isPoetry": true,
      "createdAt": "2025-04-24T01:45:09.366Z",
      "updatedAt": "2025-04-24T01:45:09.366Z",
      "chapterId": "bc971b4a-1697-40d9-a291-63723b8d05ef"
    },
    {
      "id": "5f89d657-e223-485c-9861-8b8c08b134a0",
      "number": 20,
      "content": "Họ đã đi lang thang từ nước này sang nước khác,",
      "order": 0,
      "parNumber": 27,
      "parIndex": 0,
      "isPoetry": true,
      "createdAt": "2025-04-24T01:45:09.386Z",
      "updatedAt": "2025-04-24T01:45:09.386Z",
      "chapterId": "bc971b4a-1697-40d9-a291-63723b8d05ef"
    },
    {
      "id": "d6672750-8433-429b-8c34-382b22a28635",
      "number": 20,
      "content": "Từ vương quốc nọ đến vương quốc kia.",
      "order": 1,
      "parNumber": 28,
      "parIndex": 0,
      "isPoetry": true,
      "createdAt": "2025-04-24T01:45:09.399Z",
      "updatedAt": "2025-04-24T01:45:09.399Z",
      "chapterId": "bc971b4a-1697-40d9-a291-63723b8d05ef"
    },
    {
      "id": "86f97c42-da68-4442-945e-7fef96bb4fb7",
      "number": 21,
      "content": "Nhưng Ngài đã không cho phép ai hà hiếp họ;",
      "order": 0,
      "parNumber": 29,
      "parIndex": 0,
      "isPoetry": true,
      "createdAt": "2025-04-24T01:45:09.413Z",
      "updatedAt": "2025-04-24T01:45:09.413Z",
      "chapterId": "bc971b4a-1697-40d9-a291-63723b8d05ef"
    },
    {
      "id": "ab182d00-455a-4727-b590-097f72d613b1",
      "number": 21,
      "content": "Vì cớ họ, Ngài đã quở trách các vua,",
      "order": 1,
      "parNumber": 30,
      "parIndex": 0,
      "isPoetry": true,
      "createdAt": "2025-04-24T01:45:09.427Z",
      "updatedAt": "2025-04-24T01:45:09.427Z",
      "chapterId": "bc971b4a-1697-40d9-a291-63723b8d05ef"
    },
    {
      "id": "8c12b4ab-6b34-4645-a51a-a5faaf5ca332",
      "number": 22,
      "content": "“Đừng đụng đến những người được xức dầu của Ta;",
      "order": 0,
      "parNumber": 31,
      "parIndex": 0,
      "isPoetry": true,
      "createdAt": "2025-04-24T01:45:09.440Z",
      "updatedAt": "2025-04-24T01:45:09.440Z",
      "chapterId": "bc971b4a-1697-40d9-a291-63723b8d05ef"
    },
    {
      "id": "165c19d3-c85c-4d36-b247-8ee30c5cff7b",
      "number": 22,
      "content": "Chớ làm hại các tiên tri của Ta.”",
      "order": 1,
      "parNumber": 32,
      "parIndex": 0,
      "isPoetry": true,
      "createdAt": "2025-04-24T01:45:09.454Z",
      "updatedAt": "2025-04-24T01:45:09.454Z",
      "chapterId": "bc971b4a-1697-40d9-a291-63723b8d05ef"
    },
    {
      "id": "18f90a8a-d0db-44b1-a21a-faea68a9ab89",
      "number": 23,
      "content": "Hỡi cả thế giới, hãy ca ngợi **CHÚA**;",
      "order": 0,
      "parNumber": 33,
      "parIndex": 0,
      "isPoetry": true,
      "createdAt": "2025-04-24T01:45:09.467Z",
      "updatedAt": "2025-04-24T01:45:09.467Z",
      "chapterId": "bc971b4a-1697-40d9-a291-63723b8d05ef"
    },
    {
      "id": "59437f01-94f7-4936-bf4b-5976fa72d31a",
      "number": 23,
      "content": "Hãy rao truyền ơn cứu rỗi của Ngài từ ngày nọ sang ngày kia.",
      "order": 1,
      "parNumber": 34,
      "parIndex": 0,
      "isPoetry": true,
      "createdAt": "2025-04-24T01:45:09.481Z",
      "updatedAt": "2025-04-24T01:45:09.481Z",
      "chapterId": "bc971b4a-1697-40d9-a291-63723b8d05ef"
    },
    {
      "id": "bd7f98e7-aba3-4d69-a8e8-1a821e615ee8",
      "number": 24,
      "content": "Hãy công bố vinh hiển của Ngài giữa các quốc gia,",
      "order": 0,
      "parNumber": 35,
      "parIndex": 0,
      "isPoetry": true,
      "createdAt": "2025-04-24T01:45:09.495Z",
      "updatedAt": "2025-04-24T01:45:09.495Z",
      "chapterId": "bc971b4a-1697-40d9-a291-63723b8d05ef"
    },
    {
      "id": "e72769e0-f22f-4aa8-a254-d3f5b720c04a",
      "number": 24,
      "content": "Hãy thuật lại những việc lạ lùng của Ngài cho mọi dân tộc.",
      "order": 1,
      "parNumber": 36,
      "parIndex": 0,
      "isPoetry": true,
      "createdAt": "2025-04-24T01:45:09.509Z",
      "updatedAt": "2025-04-24T01:45:09.509Z",
      "chapterId": "bc971b4a-1697-40d9-a291-63723b8d05ef"
    },
    {
      "id": "22130095-0e8b-4a5f-8bfa-22ac808ec353",
      "number": 25,
      "content": "Vì **CHÚA** thật vĩ đại thay! Chỉ Ngài là Đấng đáng được ca tụng.",
      "order": 0,
      "parNumber": 37,
      "parIndex": 0,
      "isPoetry": true,
      "createdAt": "2025-04-24T01:45:09.522Z",
      "updatedAt": "2025-04-24T01:45:09.522Z",
      "chapterId": "bc971b4a-1697-40d9-a291-63723b8d05ef"
    },
    {
      "id": "27afe3ab-8ff6-496c-80db-c715a16bd6e2",
      "number": 25,
      "content": "Ngài là Đấng đáng kính sợ hơn tất cả các thần.",
      "order": 1,
      "parNumber": 38,
      "parIndex": 0,
      "isPoetry": true,
      "createdAt": "2025-04-24T01:45:09.536Z",
      "updatedAt": "2025-04-24T01:45:09.536Z",
      "chapterId": "bc971b4a-1697-40d9-a291-63723b8d05ef"
    },
    {
      "id": "58e7b75f-5b61-49eb-9a93-a1dde3009b2a",
      "number": 26,
      "content": "Vì tất cả các thần của các dân chỉ là hình tượng vô tri;",
      "order": 0,
      "parNumber": 39,
      "parIndex": 0,
      "isPoetry": true,
      "createdAt": "2025-04-24T01:45:09.549Z",
      "updatedAt": "2025-04-24T01:45:09.549Z",
      "chapterId": "bc971b4a-1697-40d9-a291-63723b8d05ef"
    },
    {
      "id": "33d634c3-d93a-470f-99dd-32ec6d54591b",
      "number": 26,
      "content": "Còn **CHÚA** là Đấng đã dựng nên các từng trời.",
      "order": 1,
      "parNumber": 40,
      "parIndex": 0,
      "isPoetry": true,
      "createdAt": "2025-04-24T01:45:09.562Z",
      "updatedAt": "2025-04-24T01:45:09.562Z",
      "chapterId": "bc971b4a-1697-40d9-a291-63723b8d05ef"
    },
    {
      "id": "9c39f11b-973e-4d46-9ed9-1b9f79cba8b9",
      "number": 27,
      "content": "Huy hoàng và uy nghi ở trước mặt Ngài,",
      "order": 0,
      "parNumber": 41,
      "parIndex": 0,
      "isPoetry": true,
      "createdAt": "2025-04-24T01:45:09.576Z",
      "updatedAt": "2025-04-24T01:45:09.576Z",
      "chapterId": "bc971b4a-1697-40d9-a291-63723b8d05ef"
    },
    {
      "id": "b5b436ff-5ad8-4a45-9e0f-dbc16cafa4d7",
      "number": 27,
      "content": "Quyền năng và đẹp đẽ ở trong nơi thánh của Ngài.",
      "order": 1,
      "parNumber": 42,
      "parIndex": 0,
      "isPoetry": true,
      "createdAt": "2025-04-24T01:45:09.589Z",
      "updatedAt": "2025-04-24T01:45:09.589Z",
      "chapterId": "bc971b4a-1697-40d9-a291-63723b8d05ef"
    },
    {
      "id": "f8c5939f-443f-48d0-b223-98cc48a76c40",
      "number": 28,
      "content": "Hãy quy về cho **CHÚA**, hỡi các dòng họ của muôn dân,",
      "order": 0,
      "parNumber": 43,
      "parIndex": 0,
      "isPoetry": true,
      "createdAt": "2025-04-24T01:45:09.602Z",
      "updatedAt": "2025-04-24T01:45:09.602Z",
      "chapterId": "bc971b4a-1697-40d9-a291-63723b8d05ef"
    },
    {
      "id": "465cbead-f9f3-4881-8b27-3fc39953b3e9",
      "number": 28,
      "content": "Hãy quy về cho **CHÚA** vinh hiển và quyền năng.",
      "order": 1,
      "parNumber": 44,
      "parIndex": 0,
      "isPoetry": true,
      "createdAt": "2025-04-24T01:45:09.616Z",
      "updatedAt": "2025-04-24T01:45:09.616Z",
      "chapterId": "bc971b4a-1697-40d9-a291-63723b8d05ef"
    },
    {
      "id": "58db6cf5-e830-4fd1-b09c-33f51e49b5ee",
      "number": 29,
      "content": "Hãy quy về cho **CHÚA** vinh hiển xứng đáng với danh Ngài;",
      "order": 0,
      "parNumber": 45,
      "parIndex": 0,
      "isPoetry": true,
      "createdAt": "2025-04-24T01:45:09.630Z",
      "updatedAt": "2025-04-24T01:45:09.630Z",
      "chapterId": "bc971b4a-1697-40d9-a291-63723b8d05ef"
    },
    {
      "id": "5ff7bfdb-6815-40af-9da9-6e2582f24d13",
      "number": 29,
      "content": "Hãy đem một của lễ đến trước thánh nhan Ngài.",
      "order": 1,
      "parNumber": 46,
      "parIndex": 0,
      "isPoetry": true,
      "createdAt": "2025-04-24T01:45:09.644Z",
      "updatedAt": "2025-04-24T01:45:09.644Z",
      "chapterId": "bc971b4a-1697-40d9-a291-63723b8d05ef"
    },
    {
      "id": "f1ddd1e2-df72-4a29-ae18-18abcfe0359e",
      "number": 29,
      "content": "Hãy tôn thờ **CHÚA** trong nơi thánh tráng lệ của Ngài;",
      "order": 2,
      "parNumber": 47,
      "parIndex": 0,
      "isPoetry": true,
      "createdAt": "2025-04-24T01:45:09.657Z",
      "updatedAt": "2025-04-24T01:45:09.657Z",
      "chapterId": "bc971b4a-1697-40d9-a291-63723b8d05ef"
    },
    {
      "id": "5a5b4801-67de-40d7-a34c-5261d8d6193c",
      "number": 30,
      "content": "Hỡi cả thế giới, khá run sợ trước mặt Ngài.",
      "order": 0,
      "parNumber": 48,
      "parIndex": 0,
      "isPoetry": true,
      "createdAt": "2025-04-24T01:45:09.670Z",
      "updatedAt": "2025-04-24T01:45:09.670Z",
      "chapterId": "bc971b4a-1697-40d9-a291-63723b8d05ef"
    },
    {
      "id": "2b5ebff0-1ae7-4857-aa2b-4b4a9770699c",
      "number": 30,
      "content": "Địa cầu đã được lập vững; nó sẽ không bị chuyển dời.",
      "order": 1,
      "parNumber": 49,
      "parIndex": 0,
      "isPoetry": true,
      "createdAt": "2025-04-24T01:45:09.684Z",
      "updatedAt": "2025-04-24T01:45:09.684Z",
      "chapterId": "bc971b4a-1697-40d9-a291-63723b8d05ef"
    },
    {
      "id": "6e1e205a-56e6-408f-943c-939f0984bdb7",
      "number": 31,
      "content": "Nguyện các từng trời vui mừng, nguyện trái đất vui vẻ;",
      "order": 0,
      "parNumber": 50,
      "parIndex": 0,
      "isPoetry": true,
      "createdAt": "2025-04-24T01:45:09.697Z",
      "updatedAt": "2025-04-24T01:45:09.697Z",
      "chapterId": "bc971b4a-1697-40d9-a291-63723b8d05ef"
    },
    {
      "id": "defd76ae-199b-461a-bfd2-5ba6f7b9631c",
      "number": 31,
      "content": "Nguyện người ta nói giữa các quốc gia, “**CHÚA** trị vì!”",
      "order": 1,
      "parNumber": 51,
      "parIndex": 0,
      "isPoetry": true,
      "createdAt": "2025-04-24T01:45:09.711Z",
      "updatedAt": "2025-04-24T01:45:09.711Z",
      "chapterId": "bc971b4a-1697-40d9-a291-63723b8d05ef"
    },
    {
      "id": "67609403-b064-40ff-b3e5-c62111d63092",
      "number": 32,
      "content": "Nguyện đại dương và mọi vật trong nó gầm vang;",
      "order": 0,
      "parNumber": 52,
      "parIndex": 0,
      "isPoetry": true,
      "createdAt": "2025-04-24T01:45:09.725Z",
      "updatedAt": "2025-04-24T01:45:09.725Z",
      "chapterId": "bc971b4a-1697-40d9-a291-63723b8d05ef"
    },
    {
      "id": "f87cd903-d14a-45bf-b3d2-b5759d3b1c70",
      "number": 32,
      "content": "Nguyện đồng xanh và mọi vật trong nó mừng rỡ;",
      "order": 1,
      "parNumber": 53,
      "parIndex": 0,
      "isPoetry": true,
      "createdAt": "2025-04-24T01:45:09.738Z",
      "updatedAt": "2025-04-24T01:45:09.738Z",
      "chapterId": "bc971b4a-1697-40d9-a291-63723b8d05ef"
    },
    {
      "id": "8ddf4161-5995-4a75-9804-b143e65e2c3b",
      "number": 33,
      "content": "Bấy giờ mọi cây rừng sẽ hát ca vui vẻ,",
      "order": 0,
      "parNumber": 54,
      "parIndex": 0,
      "isPoetry": true,
      "createdAt": "2025-04-24T01:45:09.752Z",
      "updatedAt": "2025-04-24T01:45:09.752Z",
      "chapterId": "bc971b4a-1697-40d9-a291-63723b8d05ef"
    },
    {
      "id": "65d53532-5241-40e5-831a-10d8a4e2867e",
      "number": 33,
      "content": "Ở trước mặt **CHÚA**, vì Ngài sắp đến để phán xét thế gian.",
      "order": 1,
      "parNumber": 55,
      "parIndex": 0,
      "isPoetry": true,
      "createdAt": "2025-04-24T01:45:09.765Z",
      "updatedAt": "2025-04-24T01:45:09.765Z",
      "chapterId": "bc971b4a-1697-40d9-a291-63723b8d05ef"
    },
    {
      "id": "afc8eef5-29a7-48eb-91fa-b9762ee44cc6",
      "number": 34,
      "content": "Hãy cảm tạ **CHÚA**, vì Ngài rất tốt,",
      "order": 0,
      "parNumber": 56,
      "parIndex": 0,
      "isPoetry": true,
      "createdAt": "2025-04-24T01:45:09.779Z",
      "updatedAt": "2025-04-24T01:45:09.779Z",
      "chapterId": "bc971b4a-1697-40d9-a291-63723b8d05ef"
    },
    {
      "id": "6841b14c-82ee-47b2-b3bd-9f2b88aad315",
      "number": 34,
      "content": "Vì tình thương của Ngài còn đến đời đời.",
      "order": 1,
      "parNumber": 57,
      "parIndex": 0,
      "isPoetry": true,
      "createdAt": "2025-04-24T01:45:09.792Z",
      "updatedAt": "2025-04-24T01:45:09.792Z",
      "chapterId": "bc971b4a-1697-40d9-a291-63723b8d05ef"
    },
    {
      "id": "526ab009-0ab6-4e93-bd55-7f2ad6826ac7",
      "number": 35,
      "content": "Xin mọi người hãy nói,",
      "order": 0,
      "parNumber": 58,
      "parIndex": 0,
      "isPoetry": false,
      "createdAt": "2025-04-24T01:45:09.806Z",
      "updatedAt": "2025-04-24T01:45:09.806Z",
      "chapterId": "bc971b4a-1697-40d9-a291-63723b8d05ef"
    },
    {
      "id": "7503fa01-0f0e-4435-b9c1-f45c1ca24dd9",
      "number": 35,
      "content": "“Lạy **CHÚA**, Đức Chúa Trời của chúng con, xin giải cứu chúng con,",
      "order": 1,
      "parNumber": 59,
      "parIndex": 0,
      "isPoetry": true,
      "createdAt": "2025-04-24T01:45:09.819Z",
      "updatedAt": "2025-04-24T01:45:09.819Z",
      "chapterId": "bc971b4a-1697-40d9-a291-63723b8d05ef"
    },
    {
      "id": "8ff328e3-6218-49ff-ad98-6fdb7b27d4f0",
      "number": 35,
      "content": "Xin đem chúng con từ giữa các dân trở về,",
      "order": 2,
      "parNumber": 60,
      "parIndex": 0,
      "isPoetry": true,
      "createdAt": "2025-04-24T01:45:09.836Z",
      "updatedAt": "2025-04-24T01:45:09.836Z",
      "chapterId": "bc971b4a-1697-40d9-a291-63723b8d05ef"
    },
    {
      "id": "625c2b17-da0f-4063-91a6-f7a92335dc7e",
      "number": 35,
      "content": "Để chúng con cảm tạ danh thánh của Ngài,",
      "order": 3,
      "parNumber": 61,
      "parIndex": 0,
      "isPoetry": true,
      "createdAt": "2025-04-24T01:45:09.850Z",
      "updatedAt": "2025-04-24T01:45:09.850Z",
      "chapterId": "bc971b4a-1697-40d9-a291-63723b8d05ef"
    },
    {
      "id": "0b51a9bb-e342-46a3-8685-3e39f6fb9495",
      "number": 35,
      "content": "Và tôn vinh ca ngợi Ngài.",
      "order": 4,
      "parNumber": 62,
      "parIndex": 0,
      "isPoetry": true,
      "createdAt": "2025-04-24T01:45:09.863Z",
      "updatedAt": "2025-04-24T01:45:09.863Z",
      "chapterId": "bc971b4a-1697-40d9-a291-63723b8d05ef"
    },
    {
      "id": "587965da-87e2-44c3-8b2a-14fa1c6ea928",
      "number": 36,
      "content": "Chúc tụng **CHÚA**, Đức Chúa Trời của I-sơ-ra-ên,",
      "order": 0,
      "parNumber": 63,
      "parIndex": 0,
      "isPoetry": true,
      "createdAt": "2025-04-24T01:45:09.876Z",
      "updatedAt": "2025-04-24T01:45:09.876Z",
      "chapterId": "bc971b4a-1697-40d9-a291-63723b8d05ef"
    },
    {
      "id": "ccdfc02d-a849-431d-b7a1-b6f82b1397f8",
      "number": 36,
      "content": "Từ đời đời cho đến đời đời.”",
      "order": 1,
      "parNumber": 64,
      "parIndex": 0,
      "isPoetry": true,
      "createdAt": "2025-04-24T01:45:09.889Z",
      "updatedAt": "2025-04-24T01:45:09.889Z",
      "chapterId": "bc971b4a-1697-40d9-a291-63723b8d05ef"
    },
    {
      "id": "61bba655-4a4b-4d54-828a-7420672e20b5",
      "number": 36,
      "content": "Xin mọi người hãy nói, “A-men!” và hãy ca ngợi **CHÚA**!",
      "order": 2,
      "parNumber": 65,
      "parIndex": 0,
      "isPoetry": false,
      "createdAt": "2025-04-24T01:45:09.903Z",
      "updatedAt": "2025-04-24T01:45:09.903Z",
      "chapterId": "bc971b4a-1697-40d9-a291-63723b8d05ef"
    },
    {
      "id": "d3de3c91-5b6d-4ead-b3d6-8fa86bc2904e",
      "number": 37,
      "content": "Đa-vít để A-sáp và bà con của ông ấy ở lại tại đó trước Rương Giao Ước của **CHÚA**, để họ phục vụ thường xuyên mỗi ngày trước Rương Thánh như đã định.",
      "order": 0,
      "parNumber": 66,
      "parIndex": 0,
      "isPoetry": false,
      "createdAt": "2025-04-24T01:45:09.916Z",
      "updatedAt": "2025-04-24T01:45:09.916Z",
      "chapterId": "bc971b4a-1697-40d9-a291-63723b8d05ef"
    },
    {
      "id": "129e8584-8684-430f-9285-4e799755da3e",
      "number": 38,
      "content": "Ông cũng để Ô-bết Ê-đôm và sáu mươi tám người bà con của ông ấy ở lại đó. Ô-bết Ê-đôm con của Giê-đu-thun và Hô-sa đặc trách việc giữ cửa.",
      "order": 0,
      "parNumber": 66,
      "parIndex": 1,
      "isPoetry": false,
      "createdAt": "2025-04-24T01:45:09.930Z",
      "updatedAt": "2025-04-24T01:45:09.930Z",
      "chapterId": "bc971b4a-1697-40d9-a291-63723b8d05ef"
    },
    {
      "id": "132114c7-b262-4dee-a736-a2ad034e3f56",
      "number": 39,
      "content": "Ngoài ra ông cũng để Tư Tế Xa-đốc và bà con của ông ấy làm tư tế trước Đền Tạm của **CHÚA** ở nơi cao tại Ghi-bê-ôn,",
      "order": 0,
      "parNumber": 66,
      "parIndex": 2,
      "isPoetry": false,
      "createdAt": "2025-04-24T01:45:09.944Z",
      "updatedAt": "2025-04-24T01:45:09.944Z",
      "chapterId": "bc971b4a-1697-40d9-a291-63723b8d05ef"
    },
    {
      "id": "783c6968-ae59-4cd7-ac38-c2c25ff1c50b",
      "number": 40,
      "content": "để họ thường xuyên dâng các của lễ thiêu lên **CHÚA** trên bàn thờ dâng của lễ thiêu, mỗi sáng và mỗi chiều, theo như mọi điều đã ghi trong luật pháp **CHÚA** đã truyền cho I-sơ-ra-ên.",
      "order": 0,
      "parNumber": 66,
      "parIndex": 3,
      "isPoetry": false,
      "createdAt": "2025-04-24T01:45:09.957Z",
      "updatedAt": "2025-04-24T01:45:09.957Z",
      "chapterId": "bc971b4a-1697-40d9-a291-63723b8d05ef"
    },
    {
      "id": "86848ac8-3265-4e2a-ab3d-5feb17c64ebe",
      "number": 41,
      "content": "Cùng ở với họ có Hê-man, Giê-đu-thun, và những người khác đã được chọn và được nêu đích danh để lo việc tạ ơn **CHÚA**, vì tình thương của Ngài còn đến đời đời.",
      "order": 0,
      "parNumber": 66,
      "parIndex": 4,
      "isPoetry": false,
      "createdAt": "2025-04-24T01:45:09.971Z",
      "updatedAt": "2025-04-24T01:45:09.971Z",
      "chapterId": "bc971b4a-1697-40d9-a291-63723b8d05ef"
    },
    {
      "id": "7a03855d-0e50-4b12-a7d9-77b7875b7e77",
      "number": 42,
      "content": "Hê-man và Giê-đu-thun được trao cho các kèn, các khánh chiêng, và mọi thứ nhạc khí để họ lo việc tấu nhạc khi hát thánh ca thờ phượng Đức Chúa Trời. Các con của Giê-đu-thun được chỉ định túc trực nơi cổng chính.",
      "order": 0,
      "parNumber": 66,
      "parIndex": 5,
      "isPoetry": false,
      "createdAt": "2025-04-24T01:45:09.985Z",
      "updatedAt": "2025-04-24T01:45:09.985Z",
      "chapterId": "bc971b4a-1697-40d9-a291-63723b8d05ef"
    },
    {
      "id": "616dc1da-d236-4fd7-8f4f-94ca01a786cc",
      "number": 43,
      "content": "Sau đó toàn dân I-sơ-ra-ên rời nơi ấy trở về nhà họ. Đa-vít cũng trở về nhà ông và chúc phước cho gia đình ông.",
      "order": 0,
      "parNumber": 67,
      "parIndex": 0,
      "isPoetry": false,
      "createdAt": "2025-04-24T01:45:09.998Z",
      "updatedAt": "2025-04-24T01:45:09.998Z",
      "chapterId": "bc971b4a-1697-40d9-a291-63723b8d05ef"
    }
  ],
  "footnotes": [
    {
      "id": "5d9764a7-a701-4457-9eae-337ccd9a949a",
      "content": "Thi 105:6 ghi Áp-ra-ham",
      "position": 28,
      "order": 0,
      "createdAt": "2025-04-24T01:45:09.191Z",
      "updatedAt": "2025-04-24T01:45:09.191Z",
      "verseId": "e5a366f1-83ec-49ad-9056-4852c614590a",
      "chapterId": "bc971b4a-1697-40d9-a291-63723b8d05ef"
    }
  ],
  "headings": [
    {
      "id": "649ad04a-0821-4766-9cbd-7c5e39b9e160",
      "content": "Đặt Rương Giao Ước vào Đền Tạm",
      "level": 1,
      "order": 0,
      "createdAt": "2025-04-24T01:45:08.938Z",
      "updatedAt": "2025-04-24T01:45:08.938Z",
      "verseId": "49a13cff-63bd-43be-a95a-2bba74eceb39",
      "chapterId": "bc971b4a-1697-40d9-a291-63723b8d05ef"
    },
    {
      "id": "4812b1b6-9415-4e25-ac66-7e7015540e5f",
      "content": "Bài Ca Cảm Tạ của Đa-vít",
      "level": 1,
      "order": 0,
      "createdAt": "2025-04-24T01:45:09.018Z",
      "updatedAt": "2025-04-24T01:45:09.018Z",
      "verseId": "e2551a0f-d9e7-4ac9-958e-3138f3300bb6",
      "chapterId": "bc971b4a-1697-40d9-a291-63723b8d05ef"
    }
  ],
  "references": [
    {
      "id": "e708fa15-6858-4d73-a3c4-07e61ca21dd1",
      "content": "(Thi 105:1-15; 96:1-13; 106:47-48)",
      "position": 0,
      "order": 0,
      "createdAt": "2025-04-24T01:45:09.033Z",
      "updatedAt": "2025-04-24T01:45:09.033Z",
      "verseId": "e2551a0f-d9e7-4ac9-958e-3138f3300bb6",
      "chapterId": "bc971b4a-1697-40d9-a291-63723b8d05ef"
    }
  ],
  "psalmMetadata": []
}